eclib/__init__.py
eclib/config/__init__.py
eclib/config/config_constants.py
eclib/config/config_loader.py
eclib/config/http_yaml_config_loader.py
eclib/consumer/__init__.py
eclib/consumer/mqconsumer.py
eclib/consumer/mqconsumer_builder.py
eclib/msg/__init__.py
eclib/msg/message.py
eclib/msg/notification.py
eclib/msg/routing_keys.py
eclib/publisher/__init__.py
eclib/publisher/ecpublisher.py
eclib/publisher/mqpublisher.py
eclib/publisher/mqpublisher_builder.py
evilcouncil_lib-0.0.1.dist-info/LICENSE
evilcouncil_lib-0.0.1.dist-info/METADATA
evilcouncil_lib-0.0.1.dist-info/WHEEL
evilcouncil_lib-0.0.1.dist-info/top_level.txt
evilcouncil_lib-0.0.1.dist-info/RECORD
